xgae/__init__.py
xgae/engine_cli_app.py
xgae/engine/engine_base.py
xgae/engine/mcp_tool_box.py
xgae/engine/prompt_builder.py
xgae/engine/task_engine.py
xgae/engine/task_langfuse.py
xgae/engine/responser/non_stream_responser.py
xgae/engine/responser/responser_base.py
xgae/engine/responser/stream_responser.py
xgae/gaia2/are_engine.py
xgae/tools/system_tools.py
xgae/utils/__init__.py
xgae/utils/json_helpers.py
xgae/utils/llm_client.py
xgae/utils/misc.py
xgae/utils/setup_env.py
xgae/utils/xml_tool_parser.py
xgae-0.4.2.dist-info/METADATA
xgae-0.4.2.dist-info/WHEEL
xgae-0.4.2.dist-info/entry_points.txt
xgae-0.4.2.dist-info/RECORD
