Metadata-Version: 2.4
Name: xgae
Version: 0.4.2
Summary: Extreme General Agent Engine
Requires-Python: >=3.11
Requires-Dist: colorlog>=6.9.0
Requires-Dist: langchain-mcp-adapters==0.1.9
Requires-Dist: langfuse==2.60.9
Requires-Dist: litellm>=1.81.0
Requires-Dist: mcp>=1.25.0
Provides-Extra: examples
Requires-Dist: chromadb==1.1.0; extra == 'examples'
Requires-Dist: langchain-community==0.3.20; extra == 'examples'
Requires-Dist: langgraph==0.6.5; extra == 'examples'
